azapidevops/AzApi.py
azapidevops/__init__.py
azapidevops/utils/AzApi_agents.py
azapidevops/utils/AzApi_boards.py
azapidevops/utils/AzApi_repos.py
azapidevops/utils/http_client.py
azapidevops-0.0.3.dist-info/licenses/LICENSE
azapidevops-0.0.3.dist-info/METADATA
azapidevops-0.0.3.dist-info/WHEEL
azapidevops-0.0.3.dist-info/top_level.txt
azapidevops-0.0.3.dist-info/RECORD
