Metadata-Version: 2.4
Name: azapidevops
Version: 0.0.3
Summary: High level library for Azure Devops REST API interface!
Author-email: Maciej Rosinski <m.rosinski97@gmail.com>
Project-URL: Homepage, https://github.com/MRosinskiGit/AzureDevopsApi
License-File: LICENSE
Requires-Dist: requests>=2.32.3
Requires-Dist: beartype>=0.21.0
Requires-Dist: dnspython>=2.7.0
Requires-Dist: email_validator>=2.2.0
Requires-Dist: pydantic>=2.11.7
Dynamic: license-file
